pangea_multipass/__init__.py
pangea_multipass/core.py
pangea_multipass/github_reader.py
pangea_multipass/py.typed
pangea_multipass/slack_reader.py
pangea_multipass/sources/__init__.py
pangea_multipass/sources/confluence/__init__.py
pangea_multipass/sources/confluence/confluence.py
pangea_multipass/sources/gdrive/__init__.py
pangea_multipass/sources/gdrive/gdrive.py
pangea_multipass/sources/github/__init__.py
pangea_multipass/sources/github/github.py
pangea_multipass/sources/jira/__init__.py
pangea_multipass/sources/jira/jira.py
pangea_multipass/sources/slack/__init__.py
pangea_multipass/sources/slack/slack.py
pangea_multipass-0.2.0.dist-info/METADATA
pangea_multipass-0.2.0.dist-info/WHEEL
pangea_multipass-0.2.0.dist-info/RECORD
